Workbook

Sheet 📋 Résumé Exécutif
A2: YTECH SOLUTIONS Analyse Financière — Architecture Réseau Sécurisée d'Entreprise
A6: Maroc — Estimation des Coûts d'Installation, Main d'Œuvre & Ingénierie | Avril 2026
B8: SYNTHÈSE DES COÛTS
B9: CATÉGORIE | C9: ÉQUIPEMENTS | D9: MAIN D'ŒUVRE | E9: INGÉNIERIE | F9: TOTAL
B10: 🌐 Réseau & Connectivité | C10: ='🌐 Équipements Réseau'!E34 -> 771500 | D10: ='🌐 Équipements Réseau'!G34 -> 63500 | E10: ='🌐 Équipements Réseau'!I34 -> 101500 | F10: =C10+D10+E10 -> 936500
B11: 🔒 Sécurité Périmétrique | C11: ='🖥️ Serveurs & Infrastructure'!E32 -> 1257000 | D11: ='🖥️ Serveurs & Infrastructure'!G32 -> 75000 | E11: ='🖥️ Serveurs & Infrastructure'!I32 -> 159000 | F11: =C11+D11+E11 -> 1491000
B12: 🖥️ Serveurs & Infrastructure | C12: 0 | D12: 0 | E12: ='📐 Étude & Ingénierie'!F31 -> 658000 | F12: =C12+D12+E12 -> 658000
B13: 📡 DMZ & Proxy | C13: 0 | D13: 0 | E13: 0 | F13: =C13+D13+E13 -> 0
B14: 📊 Monitoring & SIEM | C14: 0 | D14: 0 | E14: 0 | F14: =C14+D14+E14 -> 0
B15: 🏢 Réseau Interne & VLAN | C15: 0 | D15: 0 | E15: 0 | F15: =C15+D15+E15 -> 0
B16: 💰 TOTAL GÉNÉRAL | C16: =SUM(C10:C15) -> 2028500 | D16: =SUM(D10:D15) -> 138500 | E16: =SUM(E10:E15) -> 918500 | F16: =SUM(F10:F15) -> 3085500
B18: ⚠️ Notes : Prix indicatifs en MAD TTC basés sur le marché marocain (Avril 2026). Équipements redondants de marques différentes (ex: Cisco + Fortinet, HPE + Dell). TVA 20% incluse. Délai de livraison estimé : 8–12 semaines. La main d'œuvre inclut installation, câblage, configuration et tests.

Sheet 🌐 Équipements Réseau
A2: Équipements Réseau & Sécurité
A4: Routeurs · Firewalls · Switches · VPN · Load Balancer — Marques redondantes différenciées
B6: COMPOSANT / MARQUE | C6: ZONE | D6: QTÉ | E6: PRIX UNIT. (MAD) | F6: TOTAL ÉQUIP. (MAD) | G6: MO UNIT. (MAD) | H6: TOTAL MO (MAD) | I6: INGÉNIERIE (MAD) | J6: TOTAL (MAD)
B7: ── ROUTEURS (Marques différentes pour redondance) ──
B8: Cisco ASR 1001-X Router (Router 1 - Primary ISP) | C8: Internet / WAN | D8: 1 | E8: 85000 | F8: =D8*E8 -> 85000 | G8: 4500 | H8: =D8*G8 -> 4500 | I8: 8000 | J8: =F8+H8+I8 -> 97500
B9: MikroTik CCR2004-1G-12S+2XS (Router 2 - Backup ISP) | C9: Internet / WAN | D9: 1 | E9: 18000 | F9: =D9*E9 -> 18000 | G9: 3500 | H9: =D9*G9 -> 3500 | I9: 6000 | J9: =F9+H9+I9 -> 27500
B10: ── FIREWALLS (HA Cluster — Marques différentes) ──
B11: OPNsense Business Edition (Deciso DEC750 Appliance) — Firewall 1 (Primary) | C11: Perimeter Security | D11: 1 | E11: 21000 | F11: =D11*E11 -> 21000 | G11: 5000 | H11: =D11*G11 -> 5000 | I11: 8000 | J11: =F11+H11+I11 -> 34000
B12: Palo Alto Networks PA-820 (Firewall 2 - Secondary) | C12: Perimeter Security | D12: 1 | E12: 110000 | F12: =D12*E12 -> 110000 | G12: 5000 | H12: =D12*G12 -> 5000 | I12: 12000 | J12: =F12+H12+I12 -> 127000
B13: ── WEB APPLICATION FIREWALL ──
B14: F5 BIG-IP i2600 — WAF (Primary) | C14: DMZ | D14: 1 | E14: 120000 | F14: =D14*E14 -> 120000 | G14: 6000 | H14: =D14*G14 -> 6000 | I14: 15000 | J14: =F14+H14+I14 -> 141000
B15: ── IDS / IPS ──
B16: Suricata IDS/IPS (Licence + Appliance Dell R350) | C16: Monitoring Zone | D16: 1 | E16: 28000 | F16: =D16*E16 -> 28000 | G16: 3000 | H16: =D16*G16 -> 3000 | I16: 5000 | J16: =F16+H16+I16 -> 36000
B17: ── PARE-FEU DE SEGMENTATION INTERNE ──
B18: Check Point 1570 (Internal Segmentation Firewall) | C18: Core Network | D18: 1 | E18: 45000 | F18: =D18*E18 -> 45000 | G18: 3500 | H18: =D18*G18 -> 3500 | I18: 7000 | J18: =F18+H18+I18 -> 55500
B19: ── VPN GATEWAY ──
B20: Cisco ASA 5516-X (VPN Gateway) | C20: Perimeter Security | D20: 1 | E20: 55000 | F20: =D20*E20 -> 55000 | G20: 4000 | H20: =D20*G20 -> 4000 | I20: 8000 | J20: =F20+H20+I20 -> 67000
B21: ── LOAD BALANCER ──
B22: HAProxy Enterprise Appliance (Load Balancer) | C22: DMZ | D22: 1 | E22: 35000 | F22: =D22*E22 -> 35000 | G22: 3000 | H22: =D22*G22 -> 3000 | I22: 6000 | J22: =F22+H22+I22 -> 44000
B23: ── CORE SWITCHES (HSRP + LACP) ──
B24: Cisco Catalyst 9500-24Y4C (Core Switch 1) | C24: Core Network | D24: 1 | E24: 75000 | F24: =D24*E24 -> 75000 | G24: 4000 | H24: =D24*G24 -> 4000 | I24: 8000 | J24: =F24+H24+I24 -> 87000
B25: Juniper EX4650-48Y (Core Switch 2 — redondance) | C25: Core Network | D25: 1 | E25: 78000 | F25: =D25*E25 -> 78000 | G25: 4000 | H25: =D25*G25 -> 4000 | I25: 8000 | J25: =F25+H25+I25 -> 90000
B26: ── ACCESS SWITCHES ──
B27: Cisco Catalyst 2960X-48FPS-L (Access Switch 1) | C27: Access Layer | D27: 1 | E27: 22000 | F27: =D27*E27 -> 22000 | G27: 2500 | H27: =D27*G27 -> 2500 | I27: 3500 | J27: =F27+H27+I27 -> 28000
B28: Cisco Catalyst 2960X-48FPS-L (Access Switch 2) | C28: Access Layer | D28: 1 | E28: 22000 | F28: =D28*E28 -> 22000 | G28: 2500 | H28: =D28*G28 -> 2500 | I28: 3500 | J28: =F28+H28+I28 -> 28000
B29: Cisco Catalyst 2960X-48FPS-L (Access Switch 3) | C29: Access Layer | D29: 1 | E29: 22000 | F29: =D29*E29 -> 22000 | G29: 2500 | H29: =D29*G29 -> 2500 | I29: 3500 | J29: =F29+H29+I29 -> 28000
B30: ── CÂBLAGE, PATCHS & ACCESSOIRES ──
B31: Câbles Cat6A STP (bobines + connecteurs) — lot | C31: Tous | D31: 1 | E31: 18000 | F31: =D31*E31 -> 18000 | G31: 8000 | H31: =D31*G31 -> 8000 | I31: 0 | J31: =F31+H31+I31 -> 26000
B32: Baies de brassage 24U + organiseurs — lot | C32: Salle Serveur | D32: 2 | E32: 5500 | F32: =D32*E32 -> 11000 | G32: 1500 | H32: =D32*G32 -> 3000 | I32: 0 | J32: =F32+H32+I32 -> 14000
B33: Onduleurs APC Smart-UPS 3000VA (réseau) — lot | C33: Salle Serveur | D33: 2 | E33: 12000 | F33: =D33*E33 -> 24000 | G33: 1000 | H33: =D33*G33 -> 2000 | I33: 0 | J33: =F33+H33+I33 -> 26000
B34: TOTAL ÉQUIPEMENTS RÉSEAU & SÉCURITÉ | E34: =SUM(E8:E33) -> 771500 | G34: =SUM(G8:G33) -> 63500 | H34: =SUM(H8:H33) -> 66000 | I34: =SUM(I8:I33) -> 101500 | J34: =SUM(J8:J33) -> 956500

Sheet 🖥️ Serveurs & Infrastructure
A2: Serveurs & Infrastructure
A4: Serveurs HPE ProLiant — Configuration Haute Performance — Même Marque (HPE) + Dell pour backup
B6: COMPOSANT / MARQUE | C6: ZONE | D6: QTÉ | E6: PRIX UNIT. (MAD) | F6: TOTAL ÉQUIP. (MAD) | G6: MO UNIT. (MAD) | H6: TOTAL MO (MAD) | I6: INGÉNIERIE (MAD) | J6: TOTAL (MAD)
B7: ── SERVEURS WEB (DMZ) ──
B8: HPE ProLiant DL380 Gen11 — Web Server 1 (2×Xeon Gold, 256GB RAM, 4×960GB SSD NVMe) | C8: DMZ | D8: 1 | E8: 85000 | F8: =D8*E8 -> 85000 | G8: 6000 | H8: =D8*G8 -> 6000 | I8: 12000 | J8: =F8+H8+I8 -> 103000
B9: HPE ProLiant DL380 Gen11 — Web Server 2 (idem, redondance) | C9: DMZ | D9: 1 | E9: 85000 | F9: =D9*E9 -> 85000 | G9: 6000 | H9: =D9*G9 -> 6000 | I9: 12000 | J9: =F9+H9+I9 -> 103000
B10: ── SERVEUR BASE DE DONNÉES WEB ──
B11: HPE ProLiant DL560 Gen11 — Web DB (4×Xeon Gold, 512GB RAM, 8×1.92TB SSD NVMe RAID) | C11: DMZ | D11: 1 | E11: 145000 | F11: =D11*E11 -> 145000 | G11: 7000 | H11: =D11*G11 -> 7000 | I11: 18000 | J11: =F11+H11+I11 -> 170000
B12: Licence MySQL Enterprise (3 ans) | C12: DMZ | D12: 1 | E12: 35000 | F12: =D12*E12 -> 35000 | G12: 0 | H12: =D12*G12 -> 0 | I12: 3000 | J12: =F12+H12+I12 -> 38000
B13: ── SERVEURS ZONE INTERNE (HR) ──
B14: HPE ProLiant DL380 Gen11 — HR App Server (2×Xeon Gold, 256GB RAM) | C14: Internal Zone | D14: 1 | E14: 85000 | F14: =D14*E14 -> 85000 | G14: 6000 | H14: =D14*G14 -> 6000 | I14: 12000 | J14: =F14+H14+I14 -> 103000
B15: HPE ProLiant DL380 Gen11 — HR Database Server | C15: Internal Zone | D15: 1 | E15: 85000 | F15: =D15*E15 -> 85000 | G15: 6000 | H15: =D15*G15 -> 6000 | I15: 12000 | J15: =F15+H15+I15 -> 103000
B16: ── SERVEUR BACKUP ──
B17: Dell PowerEdge R760 — Backup Server (2×Xeon Platinum, 256GB RAM, 24×4TB SAS) | C17: Internal Zone | D17: 1 | E17: 115000 | F17: =D17*E17 -> 115000 | G17: 7000 | H17: =D17*G17 -> 7000 | I17: 15000 | J17: =F17+H17+I17 -> 137000
B18: Logiciel Backup Veeam Backup & Replication (Ent+) | C18: Internal Zone | D18: 1 | E18: 28000 | F18: =D18*E18 -> 28000 | G18: 0 | H18: =D18*G18 -> 0 | I18: 4000 | J18: =F18+H18+I18 -> 32000
B19: ── MONITORING & SIEM ──
B20: HPE ProLiant DL360 Gen11 — SIEM Server (Wazuh/ELK, 2×Xeon, 128GB, 4×1.92TB SSD) | C20: Monitoring Zone | D20: 1 | E20: 75000 | F20: =D20*E20 -> 75000 | G20: 6000 | H20: =D20*G20 -> 6000 | I20: 10000 | J20: =F20+H20+I20 -> 91000
B21: HPE ProLiant DL360 Gen11 — IDS/IPS Suricata | C21: Monitoring Zone | D21: 1 | E21: 55000 | F21: =D21*E21 -> 55000 | G21: 5000 | H21: =D21*G21 -> 5000 | I21: 8000 | J21: =F21+H21+I21 -> 68000
B22: HPE ProLiant DL360 Gen11 — Monitoring Zabbix | C22: Monitoring Zone | D22: 1 | E22: 55000 | F22: =D22*E22 -> 55000 | G22: 5000 | H22: =D22*G22 -> 5000 | I22: 8000 | J22: =F22+H22+I22 -> 68000
B23: ── STOCKAGE RÉSEAU (NAS/SAN) ──
B24: HPE MSA 2062 SAN Storage (16TB SSD + 32TB HDD) | C24: Salle Serveur | D24: 1 | E24: 120000 | F24: =D24*E24 -> 120000 | G24: 8000 | H24: =D24*G24 -> 8000 | I24: 15000 | J24: =F24+H24+I24 -> 143000
B25: ── VIRTUALISATION & LICENCES ──
B26: VMware vSphere 8 — Licence Enterprise Plus (5 sockets) | C26: Infrastructure | D26: 1 | E26: 95000 | F26: =D26*E26 -> 95000 | G26: 0 | H26: =D26*G26 -> 0 | I26: 10000 | J26: =F26+H26+I26 -> 105000
B27: Windows Server 2022 Datacenter — 3 licences | C27: Infrastructure | D27: 1 | E27: 42000 | F27: =D27*E27 -> 42000 | G27: 0 | H27: =D27*G27 -> 0 | I27: 5000 | J27: =F27+H27+I27 -> 47000
B28: ── ALIMENTATION & REFROIDISSEMENT ──
B29: APC Smart-UPS 10kVA (salle serveur) | C29: Salle Serveur | D29: 2 | E29: 55000 | F29: =D29*E29 -> 110000 | G29: 3000 | H29: =D29*G29 -> 6000 | I29: 5000 | J29: =F29+H29+I29 -> 121000
B30: Climatisation Précision CRAC 10kW (Uniflair) | C30: Salle Serveur | D30: 1 | E30: 85000 | F30: =D30*E30 -> 85000 | G30: 8000 | H30: =D30*G30 -> 8000 | I30: 10000 | J30: =F30+H30+I30 -> 103000
B31: Armoire baie 42U (full équipée, PDU, rails) | C31: Salle Serveur | D31: 4 | E31: 12000 | F31: =D31*E31 -> 48000 | G31: 2000 | H31: =D31*G31 -> 8000 | I31: 0 | J31: =F31+H31+I31 -> 56000
B32: TOTAL SERVEURS & INFRASTRUCTURE | E32: =SUM(E8:E31) -> 1257000 | G32: =SUM(G8:G31) -> 75000 | H32: =SUM(H8:H31) -> 84000 | I32: =SUM(I8:I31) -> 159000 | J32: =SUM(J8:J31) -> 1591000

Sheet 📐 Étude & Ingénierie
A2: Étude, Ingénierie & Services Professionnels
A4: Architecture · Conception · Déploiement · Tests · Formation · Support
B6: PRESTATION | C6: DÉTAIL | D6: JOURS/HOMMES | E6: TARIF JOUR (MAD) | F6: TOTAL (MAD)
B7: ── PHASE 1 : ÉTUDE & CONCEPTION ──
B8: Audit de l'existant & collecte des besoins | C8: Analyse infrastructure existante | D8: 5 | E8: 3500 | F8: =D8*E8 -> 17500
B9: Conception architecture réseau détaillée | C9: Schémas Visio/Draw.io, plans d'adressage IP, VLAN | D9: 8 | E9: 3500 | F9: =D9*E9 -> 28000
B10: Plan de sécurité & politique de sécurité (PSI) | C10: Firewall rules, ACL, IDS/IPS policies | D10: 6 | E10: 4000 | F10: =D10*E10 -> 24000
B11: Étude de dimensionnement & sizing serveurs | C11: Calcul charge, redondance, scalabilité | D11: 4 | E11: 3500 | F11: =D11*E11 -> 14000
B12: Rédaction du cahier des charges technique | C12: Documentation complète pour appels d'offres | D12: 5 | E12: 3000 | F12: =D12*E12 -> 15000
B13: ── PHASE 2 : DÉPLOIEMENT & INSTALLATION ──
B14: Chef de projet réseau (coordination) | C14: Suivi planning, réunions, reporting | D14: 15 | E14: 4500 | F14: =D14*E14 -> 67500
B15: Ingénieur réseau senior (Cisco/Fortinet) | C15: Configuration routeurs, switches, VLANs | D15: 20 | E15: 4000 | F15: =D15*E15 -> 80000
B16: Ingénieur sécurité (Firewall, VPN, WAF) | C16: Config FortiGate, PA, WAF, VPN Gateway | D16: 18 | E16: 4500 | F16: =D16*E16 -> 81000
B17: Administrateur systèmes Linux/Windows | C17: Installation et config serveurs | D17: 15 | E17: 3500 | F17: =D17*E17 -> 52500
B18: Technicien câblage & infrastructure physique | C18: Câblage baies, labellisation, tests | D18: 10 | E18: 2500 | F18: =D18*E18 -> 25000
B19: ── PHASE 3 : TESTS & RECETTE ──
B20: Tests de performance réseau (benchmarking) | C20: Iperf3, tests débit, latence, QoS | D20: 5 | E20: 3500 | F20: =D20*E20 -> 17500
B21: Tests de sécurité & pentest interne | C21: Scan vulnérabilités, tests intrusion | D21: 8 | E21: 5000 | F21: =D21*E21 -> 40000
B22: Tests de basculement HA (Failover tests) | C22: Simulation pannes, mesure RTO/RPO | D22: 5 | E22: 4000 | F22: =D22*E22 -> 20000
B23: Validation et recette client | C23: Procès-verbal, corrections, signature | D23: 4 | E23: 3500 | F23: =D23*E23 -> 14000
B24: ── PHASE 4 : DOCUMENTATION & FORMATION ──
B25: Rédaction documentation technique complète | C25: Plans réseau, runbooks, procédures | D25: 8 | E25: 3000 | F25: =D25*E25 -> 24000
B26: Formation équipe IT client (2 jours) | C26: Prise en main infrastructure | D26: 2 | E26: 5000 | F26: =D26*E26 -> 10000
B27: Formation sécurité & monitoring | C27: Wazuh/ELK, Zabbix, réponse incidents | D27: 3 | E27: 5000 | F27: =D27*E27 -> 15000
B28: ── PHASE 5 : SUPPORT POST-DÉPLOIEMENT ──
B29: Support on-site post-déploiement (1 mois) | C29: Assistance quotidienne 1er mois | D29: 22 | E29: 3500 | F29: =D29*E29 -> 77000
B30: Garantie & maintenance préventive (12 mois) | C30: Visites trimestrielles + support téléphonique | D30: 12 | E30: 3000 | F30: =D30*E30 -> 36000
B31: TOTAL ÉTUDE & INGÉNIERIE | E31: =SUM(E8:E30) -> 72000 | F31: =SUM(F8:F30) -> 658000

Sheet 💰 Récapitulatif
A2: Récapitulatif Financier Global
A4: Budget total du projet — Architecture Réseau Sécurisée Ytech Solutions
B6: CATÉGORIE | C6: ÉQUIPEMENTS (MAD) | D6: MAIN D'ŒUVRE (MAD) | E6: INGÉNIERIE (MAD) | F6: TOTAL (MAD)
B7: 🌐 Réseau & Sécurité Périmétrique | C7: ='🌐 Équipements Réseau'!E34 -> 771500 | D7: ='🌐 Équipements Réseau'!G34 -> 63500 | E7: ='🌐 Équipements Réseau'!I34 -> 101500 | F7: =C7+D7+E7 -> 936500
B8: 🖥️ Serveurs & Infrastructure | C8: ='🖥️ Serveurs & Infrastructure'!E32 -> 1257000 | D8: ='🖥️ Serveurs & Infrastructure'!G32 -> 75000 | E8: ='🖥️ Serveurs & Infrastructure'!I32 -> 159000 | F8: =C8+D8+E8 -> 1491000
B9: 📐 Étude & Ingénierie (Services Prof.) | C9: 0 | D9: 0 | E9: ='📐 Étude & Ingénierie'!F31 -> 658000 | F9: =C9+D9+E9 -> 658000
B11: SOUS-TOTAL HORS TAXES (HT) | F11: =SUM(F7:F9) -> 3085500
B12: TVA (20%) | F12: =F11*0.2 -> 617100
B13: Provision pour imprévus / Contingence (10% HT) | F13: =F11*0.1 -> 308550
B15: 💰 BUDGET TOTAL ESTIMÉ TTC (avec contingence) | F15: =F11+F12+F13 -> 4011150
B18: 📅 PLANNING INDICATIF
B19: Phase 1 — Étude & Conception | E19: 2 semaines
B20: Phase 2 — Commandes & Livraison équipements | E20: 8–12 semaines
B21: Phase 3 — Déploiement & Installation | E21: 4 semaines
B22: Phase 4 — Tests & Recette | E22: 2 semaines
B23: Phase 5 — Formation & Documentation | E23: 1 semaine
B24: DURÉE TOTALE ESTIMÉE | E24: 17–21 semaines ≈ 4–5 mois
